symspellpy/__init__.py
symspellpy/abstract_distance_comparer.py
symspellpy/composition.py
symspellpy/editdistance.py
symspellpy/frequency_bigramdictionary_en_243_342.txt
symspellpy/frequency_dictionary_en_82_765.txt
symspellpy/helpers.py
symspellpy/logging.py
symspellpy/pickle_mixin.py
symspellpy/suggest_item.py
symspellpy/symspellpy.py
symspellpy/verbosity.py
symspellpy-6.8.0.dist-info/LICENSE
symspellpy-6.8.0.dist-info/METADATA
symspellpy-6.8.0.dist-info/WHEEL
symspellpy-6.8.0.dist-info/top_level.txt
symspellpy-6.8.0.dist-info/RECORD
