Metadata-Version: 2.2
Name: symspellpy
Version: 6.8.0
Summary: Python SymSpell
Author: mmb L
License: MIT License
Project-URL: Repository, https://github.com/mammothb/symspellpy
Project-URL: Documentation, https://symspellpy.readthedocs.io/en/latest
Project-URL: Changelog, https://github.com/mammothb/symspellpy/blob/master/CHANGELOG.md
Keywords: spellchecker,symspell,word segmentation
Classifier: Development Status :: 4 - Beta
Classifier: Intended Audience :: Developers
Classifier: Intended Audience :: Education
Classifier: Natural Language :: English
Classifier: License :: OSI Approved :: MIT License
Classifier: Programming Language :: Python
Classifier: Programming Language :: Python :: 3
Classifier: Programming Language :: Python :: 3.9
Classifier: Programming Language :: Python :: 3.10
Classifier: Programming Language :: Python :: 3.11
Classifier: Programming Language :: Python :: 3.12
Classifier: Programming Language :: Python :: 3.13
Requires-Python: >=3.9
License-File: LICENSE
Requires-Dist: editdistpy>=0.1.3
